[{"name":"Rr","marks":62},{"name":"zMCJEGG19","marks":29},{"name":"AwArchho","marks":40},{"name":"spy","marks":17},{"name":"1penvvGle","marks":22},{"name":"8","marks":42},{"name":"qKG8hbq","marks":82},{"name":"uJqYYRwR5Q","marks":93},{"name":"Ues1NMm","marks":85},{"name":"TsM","marks":11},{"name":"68","marks":56},{"name":"2I2G","marks":52},{"name":"5YX74qp8","marks":3},{"name":"Jbr5rZk","marks":86},{"name":"6LBDYBT","marks":7},{"name":"8NR3RQ","marks":48},{"name":"Ypk0t0c","marks":99},{"name":"Bj0jkHLJD","marks":81},{"name":"pSsocBW","marks":18},{"name":"1Mt","marks":40},{"name":"P5","marks":54},{"name":"DfTK","marks":28},{"name":"NPO2jCy","marks":16},{"name":"DW0aA","marks":17},{"name":"kIS6KVt","marks":37},{"name":"qN2Qh","marks":18},{"name":"eCE3qOH4l4","marks":74},{"name":"b","marks":35},{"name":"hCdkZsn3Ik","marks":47},{"name":"GUivS6kNRN","marks":96},{"name":"uhz7pu","marks":6},{"name":"26EgC7u3","marks":55},{"name":"XQ9N0g9ig8","marks":4},{"name":"z1Kg","marks":19},{"name":"uFZJcD2","marks":54},{"name":"i","marks":98},{"name":"tM3","marks":99},{"name":"bqrsNre6","marks":59},{"name":"1","marks":37},{"name":"A6C","marks":94},{"name":"cQi2mbARy","marks":84},{"name":"MZ","marks":63},{"name":"GQ","marks":71},{"name":"TKxQbayoln","marks":48},{"name":"DcRicXfA","marks":54},{"name":"UTIJAGByS","marks":11},{"name":"AcxmFcUA","marks":86},{"name":"ARWQ","marks":72},{"name":"ge5Pi","marks":23},{"name":"mYq3M","marks":71},{"name":"JacFzhSRu","marks":26},{"name":"ZY3Jc","marks":99},{"name":"s1bECwhm","marks":49},{"name":"F36","marks":37},{"name":"OxzomJ","marks":89},{"name":"mqTqr4Zev","marks":16},{"name":"Z0E","marks":98},{"name":"QEov","marks":32},{"name":"x9AZz","marks":71},{"name":"8x","marks":44},{"name":"tMUAF8","marks":47},{"name":"aMlk9Cb","marks":90},{"name":"pCYWp7RB","marks":69},{"name":"M","marks":51},{"name":"A","marks":20},{"name":"mP","marks":19},{"name":"R6ehPxVjFI","marks":58},{"name":"ba8AqRJELc","marks":1},{"name":"8pJ1zK","marks":55},{"name":"0","marks":92},{"name":"HLRJh3Q","marks":76},{"name":"hROeD","marks":27},{"name":"l","marks":14},{"name":"OfXiYXK6","marks":8},{"name":"65uV8HGFzD","marks":52},{"name":"taxKdx12el","marks":11},{"name":"8wCbP","marks":66},{"name":"ixNKHE","marks":66},{"name":"fuNoznjj","marks":4},{"name":"eh19Xi","marks":71},{"name":"FWtIomYdDn","marks":82},{"name":"pLAqrLg2Jq","marks":86},{"name":"avamR","marks":99},{"name":"purJBV","marks":39},{"name":"bC3k","marks":23},{"name":"3xrMMWmCg","marks":18},{"name":"OL","marks":58},{"name":"JMgLTKwbn","marks":71},{"name":"4QcAXF","marks":77},{"name":"QG","marks":82},{"name":"5ww","marks":49},{"name":"ll4RWipV4","marks":58},{"name":"QTzc","marks":42},{"name":"h0E","marks":44},{"name":"xc","marks":71},{"name":"aTaYY7X","marks":37},{"name":"iFvKBpY","marks":23},{"name":"VBDbnONCI3","marks":8},{"name":"VPmW59","marks":56},{"name":"ZwU99n7r","marks":99}]
